seededpf/README.md
seededpf/SPF_helper.py
seededpf/SPF_model.py
seededpf/__init__.py
seededpf/spf_graphical.PNG
seededpf/utils.py
seededpf-0.1.1.dist-info/LICENSE
seededpf-0.1.1.dist-info/METADATA
seededpf-0.1.1.dist-info/WHEEL
seededpf-0.1.1.dist-info/RECORD
