Metadata-Version: 2.3
Name: seededPF
Version: 0.1.1
Summary: SeededPF is a seed guided topic model based on Poisson factorization.
License: MIT
Keywords: nlp,topicmodel,topic-modeling,textanalysis,text mining
Author: Bernd Prostmaier
Author-email: b.prostmaier@icloud.com
Requires-Python: >=3.10,<3.12
Classifier: License :: OSI Approved :: MIT License
Classifier: Programming Language :: Python :: 3
Classifier: Programming Language :: Python :: 3.10
Classifier: Programming Language :: Python :: 3.11
Requires-Dist: cmake (==3.31.6)
Requires-Dist: matplotlib
Requires-Dist: numpy (>=1.23,<2.0)
Requires-Dist: pandas
Requires-Dist: scikit_learn (==1.6.1)
Requires-Dist: scipy (==1.15.2)
Requires-Dist: seaborn (==0.13.2)
Requires-Dist: tensorflow (==2.18)
Requires-Dist: tensorflow_probability (==0.25)
Requires-Dist: tf-keras (==2.18)
Project-URL: Homepage, https://github.com/BPro2410/Seeded-Poisson-Factorization
Project-URL: Repository, https://github.com/BPro2410/Seeded-Poisson-Factorization
